<?xml version="1.0" encoding="utf-8"?>
<resources>
  <string name="broadcasts">Емитовање</string>
  <string name="liveBroadcasts">Уживо емитовање турнира</string>
  <string name="newBroadcast">Ново емитовање уживо</string>
  <string name="ongoing">У току</string>
  <string name="upcoming">Предстојеће</string>
  <string name="completed">Завршено</string>
  <string name="eventName">Назив догађаја</string>
  <string name="eventDescription">Кратак опис догађаја</string>
  <string name="fullDescription">Детаљан опис догађаја</string>
  <string name="fullDescriptionHelp">Optional long description of the broadcast. %1$s is available. Length must be less than %2$s characters.</string>
  <string name="sourceUrl">Изворни УРЛ</string>
  <string name="sourceUrlHelp">УРЛ који ће Lishogi користити да прибави ажурирања PGN. Мора бити јавно доступан.</string>
  <string name="roundNumber">Заокружен број</string>
  <string name="startDate">Датум почетка у твојој временској зони</string>
  <string name="startDateHelp">Произвољно, уколико знате кад догађај почиње</string>
  <string name="credits">Credit the source</string>
  <string name="cloneBroadcast">Клонирај емитовање</string>
  <string name="resetBroadcast">Ресетуј емитовање</string>
</resources>
