<?xml version='1.0' encoding='utf-8'?>
<resources><string name="team">Tim</string>
  <string name="teams">Timovi</string>
  <plurals name="nbMembers">
    <item quantity="one">%s član</item>
    <item quantity="few">%s člana</item>
    <item quantity="other">%s članova</item>
  </plurals>
  <string name="allTeams">Svi timovi</string>
  <string name="newTeam">Novi tim</string>
  <string name="myTeams">Moji timovi</string>
  <string name="noTeamFound">Nije pronađen nijednan tim</string>
  <string name="joinTeam">Pridružite se timu</string>
  <string name="quitTeam">Napustite tim</string>
  <string name="anyoneCanJoin">Slobodno za sve</string>
  <string name="aConfirmationIsRequiredToJoin">Za pridruživanje je potrebna potvrda</string>
  <string name="joiningPolicy">Pravila pridruživanja</string>
  <string name="teamBestPlayers">Najbolji igrači</string>
  <string name="teamRecentMembers">Najnoviji članovi</string>
  <string name="kickSomeone">Izbacite nekoga iz tima</string>
  <string name="whoToKick">Koga želite da izbacite iz tima?</string>
  <plurals name="xJoinRequests">
    <item quantity="one">%s zahtjev za pridruživanje</item>
    <item quantity="few">%s zahtjeva za pridruživanje</item>
    <item quantity="other">%s zahtjeva za pridruživanje</item>
  </plurals>
  <string name="willBeReviewed">Vođa tima će pregledati Vaš zahtjev za pridruživanje.</string>
  <string name="beingReviewed">Vođa tima pregleda Vaš zahtjev za pridruživanje.</string>
  <string name="teamBattle">Bitka timova</string>
</resources>