<?xml version="1.0" encoding="utf-8"?>
<resources>
  <string name="team">Taldea</string>
  <string name="teams">Taldeak</string>
  <plurals name="nbMembers">
    <item quantity="one">%s kide</item>
    <item quantity="other">%s kide</item>
  </plurals>
  <string name="allTeams">Talde guztiak</string>
  <string name="leaderTeams" comment="This is the button for 'teams lead by you' in the teams navigation sidebar">Kapitain zaren taldeak</string>
  <string name="newTeam">Talde berria</string>
  <string name="myTeams">Nire taldeak</string>
  <string name="noTeamFound">Ez da talderik aurkitu</string>
  <string name="joinTeam">Taldean sartu</string>
  <string name="onlyLeaderLeavesTeam">Gehitu taldeko kapitain berri bat zuk utzi aurretik edo bestela itxi taldea.</string>
  <string name="quitTeam">Taldetik atera</string>
  <string name="manuallyReviewAdmissionRequests">Eskuz egiaztatu sartzeko eskaerak</string>
  <string name="manuallyReviewAdmissionRequestsHelp">Aukeratuta badago, taldera sartzeko eskaera bidali beharko da eta hori eskuz onartu edo baztertu beharko duzu.</string>
  <plurals name="teamLeaders">
    <item quantity="one">Taldearen kapitaina</item>
    <item quantity="other">Taldearen kapitainak</item>
  </plurals>
  <string name="teamRecentMembers">Kide berriak</string>
  <string name="kickSomeone">Norbait taldetik bota</string>
  <string name="whoToKick">Nor nahi duzu taldetik bota?</string>
  <plurals name="xJoinRequests">
    <item quantity="one">Sartzeko eskaera %s</item>
    <item quantity="other">Sartzeko %s eskaera</item>
  </plurals>
  <string name="willBeReviewed">Zure eskaera taldearen arduradunak gainbegiratuko du.</string>
  <string name="beingReviewed">Taldearen arduraduna zure eskaera gainbegiratzen ari da.</string>
  <string name="requestDeclined">Zure eskaera taldearen arduradunak ukatu egin du.</string>
  <string name="subToTeamMessages">Harpidetu taldearen mezuetara</string>
  <string name="teamBattle">Taldeen arteko txapelketa</string>
  <string name="teamBattleOverview">Hainbat talderen arteko txapelketa, jokalari bakoitzak bere taldearentzat irabazten ditu puntuak</string>
  <string name="teamTournament">Talde barruko txapelketa</string>
  <string name="teamTournamentOverview">Taldeko kideak diren erabiltzaileek bakarrik parte hartu dezaketen txapelketa</string>
  <string name="swissTournamentOverview">Zure taldeko kideek bakarrik parte hartu dezaketen txapelketa suitzarra</string>
  <string name="messageAllMembers">Kide guztiei mezua bidali</string>
  <string name="messageAllMembersOverview">Taldeko kide guztiei mezu pribatu bat bidali</string>
  <string name="messageAllMembersLongDescription">Taldearen kide guztiei mezua bidali-
Adibidez talde barruko edo taldeen arteko txapelketetan parte hartzeko deialdiak egiteko erabili dezakezu.
Kontuz, agian mezurik jaso nahi ez duten erabiltzaileek taldea utziko dute-eta.</string>
  <string name="teamsIlead">Kapitain naizen taldeak</string>
  <string name="youWayWantToLinkOneOfTheseTournaments">Jokatuko diren txapelketa hauetakoren baten lotura bidali nahi duzu?</string>
  <string name="leadersChat">Kapitainen txata</string>
  <string name="introduction">Sarrera</string>
  <string name="teamIntroductionHelp">Taldeen zerrendetan erakusten den deskribapen laburra. 200 karaktere gehienez.</string>
  <string name="teamDescriptionHelp">Taldearen orrialdean ikusiko den deskribapen osoa.</string>
  <string name="closeTeam">Taldea itxi</string>
  <string name="closeTeamDescription">Taldea betiko itxi.</string>
  <string name="entryCode">Taldean sartzeko kodea</string>
  <string name="entryCodeDescriptionForLeader">(Aukerakoa) Taldera sartzeko taldekideek idatzi beharko duten kodea.</string>
  <string name="incorrectEntryCode">Sarrera-kode okerra.</string>
  <string name="teamAlreadyExists">Talde hau badago.</string>
  <string name="upcomingTournaments">Hurrengo txapelketak</string>
  <string name="completedTourns">Amaitutako txapelketak</string>
  <string name="declinedRequests">Ukatutako eskaerak</string>
  <string name="joinLichessVariantTeam">Sartu %s talde ofizialera, albiste eta txapelketen berri izateko</string>
  <string name="teamPage">Taldearen orria</string>
  <string name="thisTeamBattleIsOver">Txapelketa hau amaituta dago eta taldeak ezin dira eguneratu.</string>
  <string name="listTheTeamsThatWillCompete">Zerrendatu txapelketa honetan parte hartuko duten taldeak.</string>
  <string name="oneTeamPerLine">Talde bat lerro bakoitzean. Erabili izena berez-betetzea.</string>
  <string name="oneTeamPerLineHelp">Zerrenda hau txapelketa batetik bestera kopiatu dezakezu!

Ezin duzu talde bat ezabatu bertako jokalari bat txapelketara sartu bada.</string>
  <string name="numberOfLeadsPerTeam">Talde bateko lider kopurua. Euren puntuazioen baturak taldearen puntuazioa emango du.</string>
  <string name="numberOfLeadsPerTeamHelp">Ez zenuke balio hau aldatu behar txapelketa bat hasi ostean!</string>
  <string name="innerTeam">Barruko taldea</string>
  <plurals name="battleOfNbTeams">
    <item quantity="one">Talde %sen arteko txapelketa</item>
    <item quantity="other">%s talderen arteko txapelketa</item>
  </plurals>
  <plurals name="nbLeadersPerTeam">
    <item quantity="one">Lider bat talde bakoitzeko</item>
    <item quantity="other">%s lider talde bakoitzeko</item>
  </plurals>
</resources>
